vohuudien_check/__init__.py
vohuudien_check/checker.py
vohuudien_check-0.1.0.dist-info/licenses/LICENSE
vohuudien_check-0.1.0.dist-info/METADATA
vohuudien_check-0.1.0.dist-info/WHEEL
vohuudien_check-0.1.0.dist-info/top_level.txt
vohuudien_check-0.1.0.dist-info/RECORD
