Metadata-Version: 2.4
Name: vohuudien-check
Version: 0.1.0
Summary: Kiểm tra và chuẩn hóa tên người dùng (username) theo quy tắc PyPI
Home-page: https://github.com/<username>/vohuudien-check
Author: Võ Hữu Điền
License: MIT
License-File: LICENSE
Dynamic: author
Dynamic: description
Dynamic: description-content-type
Dynamic: home-page
Dynamic: license
Dynamic: license-file
Dynamic: summary
